egraphics/__init__.py
pymaker/__init__.py
PyMakerEngine-0.0.3.dist-info/LICENSE
PyMakerEngine-0.0.3.dist-info/METADATA
PyMakerEngine-0.0.3.dist-info/WHEEL
PyMakerEngine-0.0.3.dist-info/top_level.txt
PyMakerEngine-0.0.3.dist-info/RECORD
