Metadata-Version: 2.1
Name: PyMakerEngine
Version: 0.0.3
Summary: Make games with python
Home-page: https://discord.gg/9nTu3kW
Author: iByNiki_
Author-email: therealpingmc@gmail.com
License: UNKNOWN
Keywords: games,python games,game,pygame
Platform: UNKNOWN
Classifier: Programming Language :: Python :: 3
Classifier: License :: OSI Approved :: MIT License
Classifier: Operating System :: OS Independent
Requires-Dist: keyboard (==0.13.3)
